snpmerge/__init__.py
snpmerge/mul.py
snpmerge-0.2.0.dist-info/WHEEL
snpmerge-0.2.0.dist-info/METADATA
snpmerge-0.2.0.dist-info/RECORD
